Metadata-Version: 2.1
Name: gfit
Version: 0.2
Summary: Fast multi-gaussian curve fitting
Home-page: https://github.com/samthiele/gfit
Author: Sam Thiele
Author-email: sam.thiele01@gmail.com
License: MIT
Project-URL: Source, https://github.com/samthiele/gfit
Keywords: gaussian data fitting spectral features
Platform: UNKNOWN
Classifier: Development Status :: 3 - Alpha
Classifier: Programming Language :: Python :: 3
Classifier: Intended Audience :: Science/Research
Classifier: License :: OSI Approved :: MIT License
Classifier: Operating System :: OS Independent
Classifier: Topic :: Scientific/Engineering
Requires-Python: >=3.6
